{
  "FictionalCharacters": [
    {
      "id": "fc1",
      "name": "Narrator",
      "feels": [
        {
          "name": "Fear",
          "hasIntensity": 0.9,
          "causedBy": {
            "id": "event1",
            "name": "Whiteness of the whale"
          },
          "hasObject": {
            "id": "object1",
            "name": "Whale"
          }
        },
        {
          "name": "Amazement",
          "hasIntensity": 0.7,
          "causedBy": {
            "id": "event2",
            "name": "Mystical horror"
          },
          "hasObject": {
            "id": "object2",
            "name": "Horror"
          }
        }
      ]
    }
  ],
  "Places": [],
  "Events": [
    {
      "id": "event1",
      "name": "Whiteness of the whale",
      "takePlaceAt": null,
      "hasParticipant": {
        "id": "fc1"
      }
    },
    {
      "id": "event2",
      "name": "Mystical horror",
      "takePlaceAt": null,
      "hasParticipant": {
        "id": "fc1"
      }
    }
  ]
}
