{
  "FictionalCharacters": [
    {
      "id": "fc1",
      "name": "American Whalemen",
      "feels": [
        {
          "name": "Anticipation",
          "hasIntensity": 0.9,
          "causedBy": {
            "id": "event1",
            "name": "Approaching home with empty cargo"
          },
          "hasObject": {
            "id": "object1",
            "name": "Capturing one more whale"
          }
        },
        {
          "name": "Hope",
          "hasIntensity": 0.8,
          "causedBy": {
            "id": "event2",
            "name": "Keeping mast-heads manned"
          },
          "hasObject": {
            "id": "object2",
            "name": "Capturing one more whale"
          }
        }
      ]
    }
  ],
  "Places": [
    {
      "id": "place1",
      "name": "On board the vessel",
      "description": "At the mast-heads of the ship"
    }
  ],
  "Events": [
    {
      "id": "event1",
      "name": "Approaching home with empty cargo",
      "takePlaceAt": {
        "id": "place1"
      },
      "hasParticipant": {
        "id": "fc1"
      }
    },
    {
      "id": "event2",
      "name": "Keeping mast-heads manned",
      "takePlaceAt": {
        "id": "place1"
      },
      "hasParticipant": {
        "id": "fc1"
      }
    }
  ]
}
