{
  "FictionalCharacters": [
    {
      "id": "fc1",
      "name": "Narrator",
      "feels": [
        {
          "name": "Fear",
          "hasIntensity": 0.9,
          "causedBy": {
            "id": "event1",
            "name": "Feeling something fatally wrong"
          },
          "hasObject": {
            "id": "object1",
            "name": "Unknown danger"
          },
          "place": {
            "id": "place1",
            "name": "On the ship's deck",
            "description": "In the darkness of the night"
          }
        },
        {
          "name": "Surprise",
          "hasIntensity": 0.7,
          "causedBy": {
            "id": "event2",
            "name": "Realizing facing the ship's stern"
          },
          "hasObject": {
            "id": "object2",
            "name": "Ship's stern"
          },
          "place": {
            "id": "place1"
          }
        },
        {
          "name": "Relief",
          "hasIntensity": 0.8,
          "causedBy": {
            "id": "event3",
            "name": "Preventing the vessel from capsizing"
          },
          "hasObject": {
            "id": "object3",
            "name": "Safety"
          },
          "place": {
            "id": "place1"
          }
        },
        {
          "name": "Acceptance",
          "hasIntensity": 0.6,
          "causedBy": {
            "id": "event4",
            "name": "Learning from the experience"
          },
          "hasObject": {
            "id": "object4",
            "name": "Life lessons"
          },
          "place": {
            "id": "place1"
          }
        }
      ]
    }
  ],
  "Places": [
    {
      "id": "place1",
      "name": "On the ship's deck",
      "description": "In the darkness of the night"
    }
  ],
  "Events": [
    {
      "id": "event1",
      "name": "Feeling something fatally wrong",
      "takePlaceAt": {
        "id": "place1"
      },
      "hasParticipant": {
        "id": "fc1"
      }
    },
    {
      "id": "event2",
      "name": "Realizing facing the ship's stern",
      "takePlaceAt": {
        "id": "place1"
      },
      "hasParticipant": {
        "id": "fc1"
      }
    },
    {
      "id": "event3",
      "name": "Preventing the vessel from capsizing",
      "takePlaceAt": {
        "id": "place1"
      },
      "hasParticipant": {
        "id": "fc1"
      }
    },
    {
      "id": "event4",
      "name": "Learning from the experience",
      "takePlaceAt": {
        "id": "place1"
      },
      "hasParticipant": {
        "id": "fc1"
      }
    }
  ]
}
