{
  "FictionalCharacters": [
    {
      "id": "fc1",
      "name": "Flask",
      "feels": [
        {
          "name": "Fear",
          "hasIntensity": 0.7,
          "causedBy": {
            "id": "event1",
            "name": "Encountering whales"
          },
          "hasObject": {
            "id": "object1",
            "name": "Whales"
          }
        },
        {
          "name": "Amusement",
          "hasIntensity": 0.6,
          "causedBy": {
            "id": "event2",
            "name": "Following whales for fun"
          },
          "hasObject": {
            "id": "object2",
            "name": "Whales"
          }
        }
      ]
    },
    {
      "id": "fc2",
      "name": "Starbuck",
      "feels": [
        {
          "name": "Anticipation",
          "hasIntensity": 0.8,
          "causedBy": {
            "id": "event3",
            "name": "Preparing for battle with whales"
          },
          "hasObject": {
            "id": "object3",
            "name": "Whales"
          }
        }
      ]
    }
  ],
  "Places": [
    {
      "id": "place1",
      "name": "On board of the Pequod",
      "description": "A whaling ship"
    }
  ],
  "Events": [
    {
      "id": "event1",
      "name": "Encountering whales",
      "takePlaceAt": {
        "id": "place1"
      },
      "hasParticipant": {
        "id": "fc1"
      }
    },
    {
      "id": "event2",
      "name": "Following whales for fun",
      "takePlaceAt": {
        "id": "place1"
      },
      "hasParticipant": {
        "id": "fc1"
      }
    },
    {
      "id": "event3",
      "name": "Preparing for battle with whales",
      "takePlaceAt": {
        "id": "place1"
      },
      "hasParticipant": {
        "id": "fc2"
      }
    }
  ]
}
