{
  "FictionalCharacters": [
    {
      "id": "fc1",
      "name": "Flask",
      "feels": [
        {
          "name": "Anticipation",
          "hasIntensity": 0.7,
          "causedBy": {
            "id": "event1",
            "name": "Ahab shouting about whales"
          },
          "hasObject": {
            "id": "object1",
            "name": "White whale"
          }
        }
      ]
    },
    {
      "id": "fc2",
      "name": "Narrator",
      "feels": [
        {
          "name": "Interest",
          "hasIntensity": 0.6,
          "causedBy": {
            "id": "event2",
            "name": "Launching upon the deep"
          },
          "hasObject": {
            "id": "object2",
            "name": "Unshored, harbourless immensities"
          }
        }
      ]
    }
  ],
  "Places": [
    {
      "id": "place1",
      "name": "Pequod's deck",
      "description": "On a whaling ship in the middle of the ocean."
    }
  ],
  "Events": [
    {
      "id": "event1",
      "name": "Ahab shouting about whales",
      "takePlaceAt": {
        "id": "place1"
      },
      "hasParticipant": {
        "id": "fc1"
      }
    },
    {
      "id": "event2",
      "name": "Launching upon the deep",
      "takePlaceAt": {
        "id": "place1"
      },
      "hasParticipant": {
        "id": "fc2"
      }
    }
  ]
}
