{
  "FictionalCharacters": [
    {
      "id": "fc1",
      "name": "Captain Ahab",
      "feels": [
        {
          "name": "Anticipation",
          "hasIntensity": 0.9,
          "causedBy": {
            "id": "event1",
            "name": "Planning whale hunting strategies"
          },
          "hasObject": {
            "id": "object1",
            "name": "Whale hunting"
          },
          "place": {
            "id": "place1",
            "name": "Captain's Cabin",
            "description": "A small, dimly lit room with sea charts spread out"
          }
        },
        {
          "name": "Amazement",
          "hasIntensity": 0.7,
          "causedBy": {
            "id": "event2",
            "name": "Realization of the complexity of whale hunting"
          },
          "hasObject": {
            "id": "object2",
            "name": "Whale hunting strategies"
          },
          "place": {
            "id": "place1",
            "name": "Captain's Cabin",
            "description": "A small, dimly lit room with sea charts spread out"
          }
        },
        {
          "name": "Vigilance",
          "hasIntensity": 0.8,
          "causedBy": {
            "id": "event3",
            "name": "Studying whale migration patterns"
          },
          "hasObject": {
            "id": "object3",
            "name": "Whale migration"
          },
          "place": {
            "id": "place1",
            "name": "Captain's Cabin",
            "description": "A small, dimly lit room with sea charts spread out"
          }
        }
      ]
    }
  ],
  "Places": [
    {
      "id": "place1",
      "name": "Captain's Cabin",
      "description": "A small, dimly lit room with sea charts spread out"
    }
  ],
  "Events": [
    {
      "id": "event1",
      "name": "Planning whale hunting strategies",
      "takePlaceAt": {
        "id": "place1"
      },
      "hasParticipant": {
        "id": "fc1"
      }
    },
    {
      "id": "event2",
      "name": "Realization of the complexity of whale hunting",
      "takePlaceAt": {
        "id": "place1"
      },
      "hasParticipant": {
        "id": "fc1"
      }
    },
    {
      "id": "event3",
      "name": "Studying whale migration patterns",
      "takePlaceAt": {
        "id": "place1"
      },
      "hasParticipant": {
        "id": "fc1"
      }
    }
  ]
}
