{
 "FictionalCharacters": [
  {
   "name": "Lucy_Honeychurch",
   "feels": [
    {
     "name": "Fear",
     "hasIntensity": 0.7,
     "quote": "She was a little frightened, both by Miss Lavish and by Mr. Eager, she knew not why.",
     "hasObject": {
      "name": "Unknown"
     },
     "causedBy": {
      "name": "Interaction_with_Miss_Lavish_and_Mr_Eager",
      "takePlaceAt": {
       "name": "Shopping_trip_and_conversation"
      },
      "hasParticipant": [
       {
        "name": "Lucy_Honeychurch"
       },
       {
        "name": "Miss_Lavish"
       },
       {
        "name": "Mr_Eager"
       }
      ]
     }
    },
    {
     "name": "Rebellion",
     "hasIntensity": 0.8,
     "quote": "For the first time Lucy’s rebellious thoughts swept out in words—for the first time in her life.",
     "hasObject": {
      "name": "Accusations"
     },
     "causedBy": {
      "name": "Mr_Eager_s_accusations",
      "takePlaceAt": {
       "name": "Conversation_in_the_shop"
      },
      "hasParticipant": [
       {
        "name": "Lucy_Honeychurch"
       },
       {
        "name": "Mr_Eager"
       }
      ]
     }
    },
    {
     "name": "Confusion",
     "hasIntensity": 0.6,
     "quote": "The well-known world had broken up, and there emerged Florence, a magic city where people thought and did the most extraordinary things.",
     "hasObject": {
      "name": "Florence"
     },
     "causedBy": {
      "name": "Realization_of_the_complexities_of_Florence",
      "takePlaceAt": {
       "name": "Newspaperroom_at_the_English_bank"
      },
      "hasParticipant": {
       "name": "Lucy_Honeychurch"
      }
     }
    }
   ]
  },
  {
   "name": "Miss_Bartlett",
   "feels": [
    {
     "name": "Curiosity",
     "hasIntensity": 0.7,
     "quote": "Miss Bartlett was full of very natural curiosity.",
     "hasObject": {
      "name": "Revelations"
     },
     "causedBy": {
      "name": "Mr_Eager_s_revelations",
      "takePlaceAt": {
       "name": "Conversation_in_the_shop"
      },
      "hasParticipant": {
       "name": "Miss_Bartlett"
      }
     }
    },
    {
     "name": "Discomfiture",
     "hasIntensity": 0.6,
     "quote": "How could you think she was defending them? said Miss Bartlett, much discomfited by the unpleasant scene.",
     "hasObject": {
      "name": "Unpleasant_scene"
     },
     "causedBy": {
      "name": "Unpleasant_scene_with_Mr_Eager",
      "takePlaceAt": {
       "name": "Conversation_in_the_shop"
      },
      "hasParticipant": [
       {
        "name": "Miss_Bartlett"
       },
       {
        "name": "Mr_Eager"
       }
      ]
     }
    }
   ]
  }
 ]
}